unglue_it_driver/__init__.py
unglue_it_driver/retrieve.py
unglue_it_driver/serializers.py
hirmeos_unglue_it-0.0.1.dist-info/LICENSE
hirmeos_unglue_it-0.0.1.dist-info/METADATA
hirmeos_unglue_it-0.0.1.dist-info/WHEEL
hirmeos_unglue_it-0.0.1.dist-info/top_level.txt
hirmeos_unglue_it-0.0.1.dist-info/RECORD
