Metadata-Version: 2.1
Name: hirmeos-unglue-it
Version: 0.0.1
Summary: Functions required by the hirmeos-unglue-it
Author-email: Cristian Garcia <cristian.garcia@ubiquitypress.com>
Classifier: Programming Language :: Python :: 3
Classifier: License :: OSI Approved :: MIT License
Classifier: Operating System :: OS Independent
Requires-Python: >=3.10
License-File: LICENSE
Requires-Dist: requests >=2.25
Requires-Dist: pydantic >=2.0
